ai_prishtina_milvus_client/__init__.py
ai_prishtina_milvus_client/advanced.py
ai_prishtina_milvus_client/advanced_search.py
ai_prishtina_milvus_client/api_integrations.py
ai_prishtina_milvus_client/batch_operations.py
ai_prishtina_milvus_client/client.py
ai_prishtina_milvus_client/cloud_storage.py
ai_prishtina_milvus_client/config.py
ai_prishtina_milvus_client/data_management.py
ai_prishtina_milvus_client/data_sources.py
ai_prishtina_milvus_client/data_validation.py
ai_prishtina_milvus_client/dev_tools.py
ai_prishtina_milvus_client/distributed.py
ai_prishtina_milvus_client/error_recovery.py
ai_prishtina_milvus_client/exceptions.py
ai_prishtina_milvus_client/integrations.py
ai_prishtina_milvus_client/monitoring.py
ai_prishtina_milvus_client/performance.py
ai_prishtina_milvus_client/security.py
ai_prishtina_milvus_client/streaming.py
ai_prishtina_milvus_client-1.0.1.dist-info/METADATA
ai_prishtina_milvus_client-1.0.1.dist-info/WHEEL
ai_prishtina_milvus_client-1.0.1.dist-info/licenses/LICENSE
ai_prishtina_milvus_client-1.0.1.dist-info/licenses/LICENSE-COMMERCIAL.md
ai_prishtina_milvus_client-1.0.1.dist-info/licenses/LICENSE-NOTICE.md
ai_prishtina_milvus_client-1.0.1.dist-info/RECORD
