Metadata-Version: 2.4
Name: ai-prishtina-milvus-client
Version: 1.0.1
Summary: A comprehensive, production-ready Python client library for Milvus vector database operations designed for AI and machine learning applications
Project-URL: Homepage, https://github.com/albanmaxhuni/ai-prishtina-milvus-client
Project-URL: Documentation, https://github.com/albanmaxhuni/ai-prishtina-milvus-client/blob/main/README.md
Project-URL: Repository, https://github.com/albanmaxhuni/ai-prishtina-milvus-client.git
Project-URL: Issues, https://github.com/albanmaxhuni/ai-prishtina-milvus-client/issues
Project-URL: Changelog, https://github.com/albanmaxhuni/ai-prishtina-milvus-client/releases
Project-URL: Bug Reports, https://github.com/albanmaxhuni/ai-prishtina-milvus-client/issues
Project-URL: Source Code, https://github.com/albanmaxhuni/ai-prishtina-milvus-client
Author-email: Alban Maxhuni <alban.q.maxhuni@gmail.com>, AI Prishtina <info@albanmaxhuni.com>
License: AGPL-3.0-or-later OR Commercial
License-File: LICENSE
License-File: LICENSE-COMMERCIAL.md
License-File: LICENSE-NOTICE.md
Keywords: ai,embeddings,machine-learning,milvus,similarity-search,vector-database,vector-search
Classifier: Development Status :: 5 - Production/Stable
Classifier: Intended Audience :: Developers
Classifier: Intended Audience :: Science/Research
Classifier: License :: OSI Approved :: GNU Affero General Public License v3 or later (AGPLv3+)
Classifier: Operating System :: OS Independent
Classifier: Programming Language :: Python :: 3
Classifier: Programming Language :: Python :: 3.9
Classifier: Programming Language :: Python :: 3.10
Classifier: Programming Language :: Python :: 3.11
Classifier: Programming Language :: Python :: 3.12
Classifier: Topic :: Database
Classifier: Topic :: Internet :: WWW/HTTP :: Indexing/Search
Classifier: Topic :: Scientific/Engineering :: Artificial Intelligence
Classifier: Topic :: Software Development :: Libraries :: Python Modules
Classifier: Typing :: Typed
Requires-Python: >=3.9
Requires-Dist: aiofiles>=23.0.0
Requires-Dist: azure-identity>=1.0.0
Requires-Dist: azure-storage-blob>=12.0.0
Requires-Dist: bcrypt>=4.0.1
Requires-Dist: boto3>=1.34.0
Requires-Dist: confluent-kafka>=2.3.0
Requires-Dist: cryptography>=41.0.4
Requires-Dist: google-cloud-aiplatform>=1.36.0
Requires-Dist: google-cloud-storage>=2.0.0
Requires-Dist: h5py>=3.10.0
Requires-Dist: numpy>=1.24.0
Requires-Dist: pandas>=2.0.0
Requires-Dist: pdf2image>=1.16.3
Requires-Dist: pillow>=10.0.0
Requires-Dist: psutil>=5.9.0
Requires-Dist: pyarrow>=15.0.0
Requires-Dist: pydantic-settings>=2.0.0
Requires-Dist: pydantic>=2.4.0
Requires-Dist: pyjwt>=2.8.0
Requires-Dist: pymilvus>=2.3.0
Requires-Dist: pytesseract>=0.3.10
Requires-Dist: pyyaml>=6.0.0
Requires-Dist: redis>=5.0.0
Requires-Dist: requests>=2.0.0
Requires-Dist: sentence-transformers>=2.2.2
Requires-Dist: torch>=2.0.0
Requires-Dist: transformers>=4.30.0
Provides-Extra: dev
Requires-Dist: black>=23.0.0; extra == 'dev'
Requires-Dist: isort>=5.12.0; extra == 'dev'
Requires-Dist: mypy>=1.0.0; extra == 'dev'
Requires-Dist: pre-commit>=3.0.0; extra == 'dev'
Requires-Dist: pytest-cov>=4.0.0; extra == 'dev'
Requires-Dist: pytest>=7.0.0; extra == 'dev'
Requires-Dist: ruff>=0.1.0; extra == 'dev'
